ikutsu/__init__.py
ikutsu/ikutsu.py
ikutsu-0.1.2.dist-info/entry_points.txt
ikutsu-0.1.2.dist-info/WHEEL
ikutsu-0.1.2.dist-info/METADATA
ikutsu-0.1.2.dist-info/RECORD
